{
  "status": "complete",
  "key": "cifar10_up64|mamba|32|real_4dir",
  "dataset": "cifar10_up64",
  "block_type": "mamba",
  "variant": "real_4dir",
  "branch_dirs": "row,col,diag,anti_diag",
  "grid": 32,
  "sequence_length": 1024,
  "patch_size": 2,
  "seed": 0,
  "micro_batch": 128,
  "accum_steps": 1,
  "effective_batch": 128,
  "shuffle_order": false,
  "shuffle_seed": null,
  "shuffle_perm": null,
  "param_count": 283274,
  "peak_allocated_mb": 2704.13720703125,
  "peak_reserved_mb": 2944.0,
  "elapsed_sec": 230.08782939800585,
  "history": [
    {
      "epoch": 1,
      "lr": 0.001,
      "lr_scale": 1.0,
      "train_loss": 1.7389223942389855,
      "train_acc": 0.3557692307692308,
      "test_loss": 1.5077471099853517,
      "test_acc": 0.4487,
      "train_sec": 110.1977854949946,
      "eval_sec": 5.298132537995116,
      "epoch_wall_sec": 115.49591973298811
    },
    {
      "epoch": 2,
      "lr": 0.0,
      "lr_scale": 0.0,
      "train_loss": 1.4691786772165543,
      "train_acc": 0.4635416666666667,
      "test_loss": 1.5077471099853517,
      "test_acc": 0.4487,
      "train_sec": 109.18369067300227,
      "eval_sec": 5.393373354003415,
      "epoch_wall_sec": 114.5770663269941
    }
  ]
}